bookmarks/__init__.py
bookmarks/app.py
bookmarks/cli.py
bookmarks/config.py
bookmarks/core.py
bookmarks/db.py
bookmarks/web.py
artemis.bookmarks-0.0.2.dist-info/LICENSE
artemis.bookmarks-0.0.2.dist-info/METADATA
artemis.bookmarks-0.0.2.dist-info/WHEEL
artemis.bookmarks-0.0.2.dist-info/top_level.txt
artemis.bookmarks-0.0.2.dist-info/RECORD
