Metadata-Version: 2.1
Name: artemis.bookmarks
Version: 0.0.2
Summary: a small bookmark api
Home-page: https://git.artemix.space/?p=bookmarks;a=summary
Author: root
Author-email: pypi@artemix.org
License: CNPLv6
Platform: UNKNOWN
Classifier: Environment :: Console
Classifier: Operating System :: OS Independent
Classifier: Programming Language :: Python :: 3 :: Only
Classifier: Topic :: Internet
Classifier: Typing :: Typed
License-File: LICENSE
Requires-Dist: python-slugify
Requires-Dist: Flask
Requires-Dist: flask-sqlalchemy
Requires-Dist: toml
